mds_lib/__init__.py
mds_lib/commands.py
mds_lib/const.py
mds_lib/exc.py
mds_lib/base/__init__.py
mds_lib/base/config.py
mds_lib/logic/__init__.py
mds_lib/logic/init.py
mds_lib/logic/list.py
mds_lib/logic/pull.py
mds_lib/logic/push.py
mds_lib/logic/remove.py
mds_lib/logic/utils/__init__.py
mds_lib/models/__init__.py
mds_lib/models/api_models.py
mds_lib/utils/__init__.py
mds_lib/utils/request_handler.py
mds_lib/utils/singleton.py
mds_lib/utils/utils.py
mds_lib-0.0.1.dist-info/LICENSE
mds_lib-0.0.1.dist-info/METADATA
mds_lib-0.0.1.dist-info/WHEEL
mds_lib-0.0.1.dist-info/entry_points.txt
mds_lib-0.0.1.dist-info/top_level.txt
mds_lib-0.0.1.dist-info/RECORD
