Metadata-Version: 2.1
Name: mds-lib
Version: 0.0.1
Summary: Library for work with MiniDataStorage
Author: Denis Shchutkiy
Author-email: denisshchutskyi@gmail.com
License: UNKNOWN
Keywords: pip,mds_lib
Platform: UNKNOWN
Requires-Python: >=3.7
License-File: LICENSE
Requires-Dist: click (==8.1.2)
Requires-Dist: PyYAML (==6.0)
Requires-Dist: requests (==2.24.0)
